.travis.yml
LICENSE.txt
MANIFEST.in
README.rst
pyrrd.patch
requirements.txt
setup.py
stdeb.cfg
docs/Makefile
docs/make.bat
docs/source/conf.py
docs/source/index.rst
docs/source/new.rst
dprobe/cpu.py
dprobe/csvw.py
dprobe/edge.ini
dprobe/local_mod.json
dprobe/master.py
dprobe/orchester.py
dprobe/out.dot
dprobe/out.jpeg
dprobe/ping.py
dprobe/proc.py
dprobe/requirements.txt
dprobe/rrd.json
dprobe/rrd.py
dprobe/this.png
dprobe/tracker.py
dprobe/tracker2.py
dprobe/vertex.json
dsat/__init__.py
dsat/carbon.py
dsat/data.py
dsat/garbage_collector.py
dsat/linux_mtime.py
dsat/message.py
dsat/probe.py
dsat/rrd.py
dsat/state.py
dsat/xml.py
dsat.egg-info/PKG-INFO
dsat.egg-info/SOURCES.txt
dsat.egg-info/dependency_links.txt
dsat.egg-info/requires.txt
dsat.egg-info/top_level.txt
dsat/test/__init__.py
dsat/test/test_st_send_parse.py
dsat/test/test_state.py
example/cpu.py
example/csvw.py
example/edge.ini
example/local_mod.json
example/master.py
example/orchester.py
example/out.dot
example/out.jpeg
example/ping.py
example/proc.py
example/requirements.txt
example/rrd.json
example/rrd.py
example/tracker.py
example/vertex.json
mics_utils/graph_me.py
mics_utils/ping.gpl
mics_utils/plot_deriv_csv.py
mics_utils/proc.gpl
mics_utils/resend.sh
mics_utils/rrd.sh
mics_utils/universal_testing_client.py
odprobe/clock.py
odprobe/cpu.py
odprobe/cpu_clock.py
odprobe/csvw.py
odprobe/edge.ini
odprobe/local_mod.json
odprobe/master.py
odprobe/orchester.py
odprobe/ping.py
odprobe/proc.py
odprobe/rrd.json
odprobe/rrd.py
odprobe/tracker.py
odprobe/vertex.json