Metadata-Version: 1.1
Name: dsat
Version: 0.6.5
Summary: DSAT Distributed satellite tools
